MANIFEST.in
setup.py
./__init__.py
./__pkginfo__.py
./fix.py
./i18n.py
./lint.py
./meta.py
./utils.py
./xml_warnings.py
./test/unittest_fix.py
i18n/en.po
i18n/fr.po
odtlib.egg-info/PKG-INFO
odtlib.egg-info/SOURCES.txt
odtlib.egg-info/dependency_links.txt
odtlib.egg-info/top_level.txt
test/data/fixed.xml
test/data/orig.xml