Metadata-Version: 1.0
Name: odtlib
Version: 0.5.0
Summary: utility to check & fix odt files
Home-page: http://www.logilab.org/project/odtlib
Author: Logilab
Author-email: contact@logilab.fr
License: GPL
Platform: UNKNOWN
